backtest_view/__init__.py
backtest_view/__main__.py
backtest_view/cli.py
backtest_view/constants.py
backtest_view/data_source/__init__.py
backtest_view/data_source/abstract.py
backtest_view/data_source/backtest/__init__.py
backtest_view/data_source/backtest/abstract.py
backtest_view/data_source/backtest/freqtrade.py
backtest_view/data_source/database/__init__.py
backtest_view/draw/__init__.py
backtest_view/draw/plot.py
backtest_view/utilities.py
backtest_view-0.0.12.dist-info/METADATA
backtest_view-0.0.12.dist-info/WHEEL
backtest_view-0.0.12.dist-info/entry_points.txt
backtest_view-0.0.12.dist-info/RECORD
