Metadata-Version: 2.1
Name: backtest-view
Version: 0.0.12
Summary: An analysis tool for viewing and replaying backtesting results
Author: jamesbaber1
Author-email: 31859220+jamesbaber1@users.noreply.github.com
Requires-Python: >=3.11,<3.13
Classifier: License :: OSI Approved :: MIT License
Classifier: Operating System :: OS Independent
Classifier: Programming Language :: Python :: 3
Classifier: Programming Language :: Python :: 3.11
Classifier: Programming Language :: Python :: 3.12
Requires-Dist: art (>=5.8)
Requires-Dist: lightweight-charts (>=1.0.18.7)
Requires-Dist: pandas (>=2.1.3,<3.0.0)
Requires-Dist: python-dotenv (>=1.0.0,<2.0.0)
Requires-Dist: pythonnet (>=3.0.3,<4.0.0)
Requires-Dist: tomlkit (>=0.11.6)
Requires-Dist: typer[all] (>=0.7.0,<0.8.0)
